ergani/__init__.py
ergani/auth.py
ergani/client.py
ergani/exceptions.py
ergani/models.py
ergani/typings.py
ergani/utils.py
ergani-1.0.1.dist-info/LICENSE
ergani-1.0.1.dist-info/METADATA
ergani-1.0.1.dist-info/WHEEL
ergani-1.0.1.dist-info/RECORD
