Metadata-Version: 2.1
Name: ergani
Version: 1.0.1
Summary: Python SDK for the Greek government's Ergani API
License: MIT
Author: Paris Kasidiaris
Author-email: paris@withlogic.co
Requires-Python: >=3.10,<4.0
Classifier: License :: OSI Approved :: MIT License
Classifier: Programming Language :: Python :: 3
Classifier: Programming Language :: Python :: 3.10
Classifier: Programming Language :: Python :: 3.11
Classifier: Programming Language :: Python :: 3.12
Requires-Dist: requests (>=2.31.0,<3.0.0)
